python_nicepay/__init__.py
python_nicepay/__pycache__/__init__.cpython-311.pyc
python_nicepay/config/__init__.py
python_nicepay/config/apiClient.py
python_nicepay/config/__pycache__/__init__.cpython-311.pyc
python_nicepay/config/__pycache__/apiClient.cpython-311.pyc
python_nicepay/constants/__init__.py
python_nicepay/constants/constantsEndpoint.py
python_nicepay/constants/constantsGeneral.py
python_nicepay/constants/__pycache__/__init__.cpython-311.pyc
python_nicepay/constants/__pycache__/constantsEndpoint.cpython-311.pyc
python_nicepay/constants/__pycache__/constantsGeneral.cpython-311.pyc
python_nicepay/data/__init__.py
python_nicepay/data/__pycache__/__init__.cpython-311.pyc
python_nicepay/data/builder/__init__.py
python_nicepay/data/builder/builderEnvironment.py
python_nicepay/data/builder/__pycache__/__init__.cpython-311.pyc
python_nicepay/data/builder/__pycache__/builderEnvironment.cpython-311.pyc
python_nicepay/data/builder/snap/__init__.py
python_nicepay/data/builder/snap/builderAccessToken.py
python_nicepay/data/builder/snap/builderDirectDebit.py
python_nicepay/data/builder/snap/builderPayout.py
python_nicepay/data/builder/snap/builderQris.py
python_nicepay/data/builder/snap/builderVirtualAccount.py
python_nicepay/data/builder/snap/dataGenerator.py
python_nicepay/data/builder/snap/__pycache__/__init__.cpython-311.pyc
python_nicepay/data/builder/snap/__pycache__/builderAccessToken.cpython-311.pyc
python_nicepay/data/builder/snap/__pycache__/builderDirectDebit.cpython-311.pyc
python_nicepay/data/builder/snap/__pycache__/builderPayout.cpython-311.pyc
python_nicepay/data/builder/snap/__pycache__/builderVirtualAccount.cpython-311.pyc
python_nicepay/data/builder/snap/__pycache__/dataGenerator.cpython-311.pyc
python_nicepay/data/builder/v1/__init__.py
python_nicepay/data/builder/v1/__pycache__/__init__.cpython-311.pyc
python_nicepay/data/builder/v1/enterprise/__init__.py
python_nicepay/data/builder/v1/enterprise/builderCancel.py
python_nicepay-1.1.1.dist-info/METADATA
python_nicepay-1.1.1.dist-info/WHEEL
python_nicepay-1.1.1.dist-info/top_level.txt
python_nicepay-1.1.1.dist-info/RECORD
