Metadata-Version: 2.1
Name: python-nicepay
Version: 1.1.1
Summary: This is the Official Python API client / library for NICEPAY Payment API
Home-page: https://nicepay.co.id
Author: Harfa Thandila
Author-email: harfa.thandila@nicepay.co.id
Project-URL: Documentation, https://docs.nicepay.co.id/
Project-URL: Source, https://github.com/nicepay-dev/python-nicepay
Keywords: pypi,config,nicepay
Classifier: Programming Language :: Python :: 3
Requires-Dist: pycryptodome==3.21.0
Requires-Dist: requests==2.32.3
